LICENCE
README.md
setup.py
setup_C.py
periodicitytest/__init__.py
periodicitytest/_periodicitytest.c
periodicitytest/basics.h
periodicitytest/basics_python.c
periodicitytest/basics_python.h
periodicitytest/basics_standalone.c
periodicitytest/basics_standalone.h
periodicitytest/extremacounting.c
periodicitytest/extremacounting.h
periodicitytest/interval.c
periodicitytest/interval.h
periodicitytest/search.c
periodicitytest/search.h
periodicitytest/standalone.c
periodicitytest.egg-info/PKG-INFO
periodicitytest.egg-info/SOURCES.txt
periodicitytest.egg-info/dependency_links.txt
periodicitytest.egg-info/requires.txt
periodicitytest.egg-info/top_level.txt
tests/extremacounting_test.c
tests/periodicitytest_test.py
tests/search_test.c
tests/testfunctions.c
tests/testfunctions.h