Metadata-Version: 1.1
Name: periodicitytest
Version: 0.0.0
Summary: a highly specific test for periodicity of time series based on folding
Home-page: http://github.com/neurophysik/periodicitytest
Author: Gerrit Ansmann
Author-email: gansmann@uni-bonn.de
License: UNKNOWN
Platform: UNKNOWN
Classifier: Development Status :: 4 - Beta
Classifier: License :: OSI Approved :: BSD License
Classifier: Operating System :: POSIX
Classifier: Operating System :: MacOS :: MacOS X
Classifier: Operating System :: Microsoft :: Windows
Classifier: Programming Language :: Python
Classifier: Programming Language :: C
Classifier: Topic :: Scientific/Engineering :: Mathematics
